academy/__init__.py
academy/agent.py
academy/context.py
academy/event.py
academy/exception.py
academy/handle.py
academy/identifier.py
academy/logging.py
academy/manager.py
academy/message.py
academy/mypy_plugin.py
academy/py.typed
academy/runtime.py
academy/serialize.py
academy/socket.py
academy/state.py
academy/exchange/__init__.py
academy/exchange/hybrid.py
academy/exchange/local.py
academy/exchange/proxystore.py
academy/exchange/redis.py
academy/exchange/transport.py
academy/exchange/cloud/__init__.py
academy/exchange/cloud/__main__.py
academy/exchange/cloud/authenticate.py
academy/exchange/cloud/client.py
academy/exchange/cloud/config.py
academy/exchange/cloud/exceptions.py
academy/exchange/cloud/login.py
academy/exchange/cloud/server.py
academy_py-0.2.0.dist-info/licenses/LICENSE
academy_py-0.2.0.dist-info/METADATA
academy_py-0.2.0.dist-info/WHEEL
academy_py-0.2.0.dist-info/top_level.txt
academy_py-0.2.0.dist-info/RECORD
