Metadata-Version: 2.4
Name: academy-py
Version: 0.2.0
Summary: Build and deploy stateful agents across federated resources.
Author: Globus Labs
Author-email: Greg Pauloski <jgpauloski@uchicago.edu>
Maintainer-email: Greg Pauloski <jgpauloski@uchicago.edu>
License: MIT
Project-URL: Homepage, https://academy.proxystore.dev
Project-URL: Documentation, https://academy.proxystore.dev
Project-URL: Source, https://github.com/proxystore/academy
Classifier: License :: OSI Approved :: MIT License
Classifier: Programming Language :: Python :: 3
Classifier: Programming Language :: Python :: 3 :: Only
Classifier: Programming Language :: Python :: Implementation :: CPython
Requires-Python: >=3.9
License-File: LICENSE
Requires-Dist: aiohttp
Requires-Dist: aiologic
Requires-Dist: click!=8.1.4
Requires-Dist: culsans
Requires-Dist: globus_sdk<4,>=3.46
Requires-Dist: proxystore>=0.8.0
Requires-Dist: pydantic<3,>=2
Requires-Dist: redis
Requires-Dist: tomli; python_version < "3.11"
Requires-Dist: typing-extensions>=4.3.0; python_version < "3.11"
Provides-Extra: dev
Requires-Dist: covdefaults>=2.2; extra == "dev"
Requires-Dist: coverage; extra == "dev"
Requires-Dist: mypy; extra == "dev"
Requires-Dist: pre-commit; extra == "dev"
Requires-Dist: pytest; extra == "dev"
Requires-Dist: pytest-asyncio>=1; extra == "dev"
Requires-Dist: pytest-cov; extra == "dev"
Requires-Dist: ruff>=0.2.0; extra == "dev"
Requires-Dist: tox; extra == "dev"
Requires-Dist: virtualenv; extra == "dev"
Provides-Extra: docs
Requires-Dist: black==25.1.0; extra == "docs"
Requires-Dist: griffe==1.7.3; extra == "docs"
Requires-Dist: griffe-pydantic==1.1.4; extra == "docs"
Requires-Dist: mkdocs-autorefs==1.4.1; extra == "docs"
Requires-Dist: mkdocs-gen-files==0.5.0; extra == "docs"
Requires-Dist: mkdocs-literate-nav==0.6.2; extra == "docs"
Requires-Dist: mkdocs-material==9.6.12; extra == "docs"
Requires-Dist: mkdocs-section-index==0.3.10; extra == "docs"
Requires-Dist: mkdocstrings==0.29.1; extra == "docs"
Requires-Dist: mkdocstrings-python==1.16.10; extra == "docs"
Requires-Dist: mike==2.1.3; extra == "docs"
Dynamic: license-file
